[{"xid":"W597925159","name":"Mercado Municipal Benito Juarez","rate":1,"osm":"way/597925159","kinds":"shops,supermarkets,tourist_facilities","point":{"lon":-111.671722,"lat":25.033377}},{"xid":"N5284707222","name":"Ley","rate":1,"osm":"node/5284707222","kinds":"shops,supermarkets,tourist_facilities","point":{"lon":-111.66935,"lat":25.021677}},{"xid":"N5227296521","name":"El show de la salud","rate":1,"osm":"node/5227296521","kinds":"shops,supermarkets,tourist_facilities","point":{"lon":-111.672348,"lat":25.034109}},{"xid":"N5284711521","name":"Bodega Aurrera","rate":1,"osm":"node/5284711521","kinds":"shops,supermarkets,tourist_facilities","point":{"lon":-111.675705,"lat":25.040361}},{"xid":"W154147610","name":"","rate":0,"osm":"way/154147610","kinds":"shops,supermarkets,tourist_facilities","point":{"lon":-111.773849,"lat":25.251511}}]