[{"xid":"W250528045","name":"Harris Teeter","rate":1,"osm":"way/250528045","kinds":"shops,supermarkets,tourist_facilities","point":{"lon":-78.924187,"lat":36.0098}},{"xid":"W308807601","name":"Food Lion","rate":1,"osm":"way/308807601","kinds":"shops,supermarkets,tourist_facilities","point":{"lon":-78.116264,"lat":36.720219}},{"xid":"W394366000","name":"Walmart Supercenter","rate":1,"osm":"way/394366000","kinds":"shops,supermarkets,tourist_facilities","point":{"lon":-78.320564,"lat":36.083271}},{"xid":"W562035568","name":"Food Lion","rate":1,"osm":"way/562035568","kinds":"shops,supermarkets,tourist_facilities","point":{"lon":-78.496719,"lat":36.039192}},{"xid":"N266814250","name":"Whole Foods Market","rate":1,"osm":"node/266814250","kinds":"shops,supermarkets,tourist_facilities","point":{"lon":-78.920555,"lat":36.007099}},{"xid":"N297638926","name":"Harris Teeter","rate":1,"osm":"node/297638926","kinds":"shops,supermarkets,tourist_facilities","point":{"lon":-78.948578,"lat":36.018856}},{"xid":"N698789159","name":"Food Lion","rate":1,"osm":"node/698789159","kinds":"shops,supermarkets,tourist_facilities","point":{"lon":-78.977005,"lat":36.408989}},{"xid":"N1096436196","name":"Food Lion","rate":1,"osm":"node/1096436196","kinds":"shops,supermarkets,tourist_facilities","point":{"lon":-78.897324,"lat":36.686237}},{"xid":"N1595817316","name":"Food Lion","rate":1,"osm":"node/1595817316","kinds":"shops,supermarkets,tourist_facilities","point":{"lon":-78.928062,"lat":36.058308}},{"xid":"N1814139370","name":"Food Lion","rate":1,"osm":"node/1814139370","kinds":"shops,supermarkets,tourist_facilities","point":{"lon":-78.43351,"lat":36.32972}},{"xid":"N2601635418","name":"Food Lion","rate":1,"osm":"node/2601635418","kinds":"shops,supermarkets,tourist_facilities","point":{"lon":-78.569389,"lat":36.618408}},{"xid":"N2799202992","name":"Food Lion","rate":1,"osm":"node/2799202992","kinds":"shops,supermarkets,tourist_facilities","point":{"lon":-78.911255,"lat":36.076267}},{"xid":"N3201039676","name":"Food Lion","rate":1,"osm":"node/3201039676","kinds":"shops,supermarkets,tourist_facilities","point":{"lon":-78.219086,"lat":36.987206}},{"xid":"N3201091330","name":"Maxway","rate":1,"osm":"node/3201091330","kinds":"shops,supermarkets,tourist_facilities","point":{"lon":-78.447456,"lat":36.800835}},{"xid":"N3201105335","name":"Food Deals","rate":1,"osm":"node/3201105335","kinds":"shops,supermarkets,tourist_facilities","point":{"lon":-78.128899,"lat":36.727055}},{"xid":"N4284993895","name":"Just Save","rate":1,"osm":"node/4284993895","kinds":"shops,supermarkets,tourist_facilities","point":{"lon":-78.294846,"lat":36.095894}},{"xid":"N5318800468","name":"Food Lion","rate":1,"osm":"node/5318800468","kinds":"shops,supermarkets,tourist_facilities","point":{"lon":-78.181847,"lat":36.435566}},{"xid":"N5497869161","name":"Food Lion","rate":1,"osm":"node/5497869161","kinds":"shops,supermarkets,tourist_facilities","point":{"lon":-78.920242,"lat":36.730885}},{"xid":"N5497869371","name":"Shopper's Value Foods","rate":1,"osm":"node/5497869371","kinds":"shops,supermarkets,tourist_facilities","point":{"lon":-78.912338,"lat":36.714874}},{"xid":"N6478432572","name":"Food Lion","rate":1,"osm":"node/6478432572","kinds":"shops,supermarkets,tourist_facilities","point":{"lon":-78.408791,"lat":36.317043}},{"xid":"N6594802145","name":"Red Barn Food Stores","rate":1,"osm":"node/6594802145","kinds":"shops,supermarkets,tourist_facilities","point":{"lon":-78.165215,"lat":36.714401}},{"xid":"N5315601371","name":"Walmart Supercenter","rate":1,"osm":"node/5315601371","kinds":"shops,supermarkets,tourist_facilities","point":{"lon":-78.843742,"lat":36.028229}},{"xid":"W61955184","name":"Walmart Supercenter","rate":1,"osm":"way/61955184","kinds":"shops,supermarkets,tourist_facilities","point":{"lon":-78.443398,"lat":36.334839}},{"xid":"W146313026","name":"Harris Teeter","rate":1,"osm":"way/146313026","kinds":"shops,supermarkets,tourist_facilities","point":{"lon":-78.930832,"lat":36.056305}},{"xid":"W167145700","name":"Aldi","rate":1,"osm":"way/167145700","kinds":"shops,supermarkets,tourist_facilities","point":{"lon":-78.44072,"lat":36.338806}},{"xid":"W645122714","name":"Walmart Supercenter","rate":1,"osm":"way/645122714","kinds":"shops,supermarkets,tourist_facilities","point":{"lon":-78.910637,"lat":36.735806}},{"xid":"W645353124","name":"Walmart Supercenter","rate":1,"osm":"way/645353124","kinds":"shops,supermarkets,tourist_facilities","point":{"lon":-78.602776,"lat":36.279922}},{"xid":"W651886744","name":"Food Lion","rate":1,"osm":"way/651886744","kinds":"shops,supermarkets,tourist_facilities","point":{"lon":-78.465233,"lat":36.099297}},{"xid":"N6172021774","name":"Food Lion","rate":1,"osm":"node/6172021774","kinds":"shops,supermarkets,tourist_facilities","point":{"lon":-78.570526,"lat":36.317303}},{"xid":"N6463311439","name":"Food Lion","rate":1,"osm":"node/6463311439","kinds":"shops,supermarkets,tourist_facilities","point":{"lon":-78.891113,"lat":36.036415}},{"xid":"W146202920","name":"Kroger","rate":1,"osm":"way/146202920","kinds":"shops,supermarkets,tourist_facilities","point":{"lon":-78.920471,"lat":36.029762}},{"xid":"W308810149","name":"Walmart Supercenter","rate":1,"osm":"way/308810149","kinds":"shops,supermarkets,tourist_facilities","point":{"lon":-78.104965,"lat":36.712051}},{"xid":"W382891285","name":"Walmart Supercenter","rate":1,"osm":"way/382891285","kinds":"shops,supermarkets,tourist_facilities","point":{"lon":-78.984833,"lat":36.376808}},{"xid":"W656371055","name":"Harris Teeter","rate":1,"osm":"way/656371055","kinds":"shops,supermarkets,tourist_facilities","point":{"lon":-78.518318,"lat":36.005333}},{"xid":"W27266155","name":"Food Lion","rate":1,"osm":"way/27266155","kinds":"shops,supermarkets,tourist_facilities","point":{"lon":-78.934006,"lat":36.014214}},{"xid":"W78708439","name":"Red White Grocery","rate":1,"osm":"way/78708439","kinds":"shops,supermarkets,tourist_facilities","point":{"lon":-78.889519,"lat":36.019909}},{"xid":"W146154900","name":"Food Lion","rate":1,"osm":"way/146154900","kinds":"shops,supermarkets,tourist_facilities","point":{"lon":-78.979225,"lat":36.031944}},{"xid":"W630404684","name":"","rate":0,"osm":"way/630404684","kinds":"shops,supermarkets,tourist_facilities","point":{"lon":-78.144676,"lat":36.733456}},{"xid":"N3478024240","name":"","rate":0,"osm":"node/3478024240","kinds":"shops,supermarkets,tourist_facilities","point":{"lon":-78.668335,"lat":36.122501}},{"xid":"N6322252128","name":"","rate":0,"osm":"node/6322252128","kinds":"shops,supermarkets,tourist_facilities","point":{"lon":-78.463676,"lat":36.811531}}]