[{"xid":"W496144589","name":"E-Z Mart","rate":1,"osm":"way/496144589","kinds":"shops,supermarkets,tourist_facilities","point":{"lon":-94.758049,"lat":34.162636}},{"xid":"N453645440","name":"Walmart Supercenter","rate":1,"osm":"node/453645440","kinds":"shops,supermarkets,tourist_facilities","point":{"lon":-94.225853,"lat":34.588543}},{"xid":"N5315599017","name":"Walmart Supercenter","rate":1,"osm":"node/5315599017","kinds":"shops,supermarkets,tourist_facilities","point":{"lon":-94.319061,"lat":34.043472}},{"xid":"N3577835727","name":"Pruett's Foods","rate":1,"osm":"node/3577835727","kinds":"shops,supermarkets,tourist_facilities","point":{"lon":-94.73806,"lat":34.025009}},{"xid":"W373252594","name":"Walmart","rate":1,"osm":"way/373252594","kinds":"shops,supermarkets,tourist_facilities","point":{"lon":-94.737976,"lat":34.02248}}]